genetictabler/__init__.py
genetictabler-2.0.3.dist-info/LICENSE
genetictabler-2.0.3.dist-info/METADATA
genetictabler-2.0.3.dist-info/WHEEL
genetictabler-2.0.3.dist-info/top_level.txt
genetictabler-2.0.3.dist-info/RECORD
