Metadata-Version: 2.1
Name: genetictabler
Version: 2.0.3
Summary: A time table scheduler using Genetic algorithm(s).
Author: Dipan Nanda
Author-email: d19cyber@gmail.com
License: GPLv3
Project-URL: Source code, https://github.com/themagicalmammal/genetictabler
Project-URL: Documentation, https://github.com/themagicalmammal/genetictabler/blob/main/README.md
Project-URL: Bug tracker, https://github.com/themagicalmammal/genetictabler/issues
Keywords: python,geneticalgorithm,genetics,genes,chromosomes,timetable
Classifier: Development Status :: 5 - Production/Stable
Classifier: Intended Audience :: Developers
Classifier: License :: OSI Approved :: BSD License
Classifier: Natural Language :: English
Classifier: Programming Language :: Python
Classifier: Programming Language :: Python :: 3
Classifier: Operating System :: Unix
Classifier: Operating System :: MacOS :: MacOS X
Classifier: Operating System :: Microsoft :: Windows
Classifier: Topic :: Utilities
License-File: LICENSE
